helloworld.py
helloworld2020danh-0.0.1.dist-info/METADATA
helloworld2020danh-0.0.1.dist-info/WHEEL
helloworld2020danh-0.0.1.dist-info/top_level.txt
helloworld2020danh-0.0.1.dist-info/RECORD
