Metadata-Version: 2.1
Name: helloworld2020danh
Version: 0.0.1
Summary: Say Hello
Home-page: UNKNOWN
License: UNKNOWN
Platform: UNKNOWN
Classifier: Programming Language :: Python :: 3.6
Classifier: Programming Language :: Python :: 3.7
Requires-Dist: numpy (~=1.20)
Provides-Extra: dev
Requires-Dist: pytest (>=3.7) ; extra == 'dev'
